CHANGELOG.md
amarps/__init__.py
amarps/__main__.py
amarps/events.py
amarps/main.py
amarps/profile_page_selectors.yml
amarps/review_page_selectors.yml
amarps/scraper.py
amarps-0.19.0.dist-info/LICENSE
amarps-0.19.0.dist-info/METADATA
amarps-0.19.0.dist-info/WHEEL
amarps-0.19.0.dist-info/entry_points.txt
amarps-0.19.0.dist-info/RECORD
