Metadata-Version: 2.1
Name: amarps
Version: 0.19.0
Summary: Download amazon product reviews and the reviewers profile information
Home-page: https://github.com/joclement/amarps
License: MIT
Author: Joris Clement
Author-email: joclement@posteo.net
Requires-Python: >=3.8,<4.0
Classifier: License :: OSI Approved :: MIT License
Classifier: Programming Language :: Python :: 3
Classifier: Programming Language :: Python :: 3.8
Classifier: Programming Language :: Python :: 3.9
Classifier: Programming Language :: Python :: 3.10
Classifier: Programming Language :: Python :: 3.11
Requires-Dist: click (>=8,<9)
Requires-Dist: click-log (>=0.4.0,<0.5.0)
Requires-Dist: dateparser (>=1,<2)
Requires-Dist: requests (>=2,<3)
Requires-Dist: selectorlib (>=0.16,<0.17)
Requires-Dist: selenium (>=4,<5)
Requires-Dist: selenium-wire (>=5,<6)
Requires-Dist: webdriver-manager (>=3,<4)
Project-URL: Repository, https://github.com/joclement/amarps
